collective.z3cform.norobots-3.0-py3.11-nspkg.pth
collective/z3cform/norobots/__init__.py
collective/z3cform/norobots/configure.zcml
collective/z3cform/norobots/i18n.py
collective/z3cform/norobots/interfaces.py
collective/z3cform/norobots/norobots_input.pt
collective/z3cform/norobots/profiles.zcml
collective/z3cform/norobots/rebuild_i18n.sh
collective/z3cform/norobots/setuphandlers.py
collective/z3cform/norobots/testing.py
collective/z3cform/norobots/testing.zcml
collective/z3cform/norobots/validator.py
collective/z3cform/norobots/widget.py
collective/z3cform/norobots/browser/__init__.py
collective/z3cform/norobots/browser/configure.zcml
collective/z3cform/norobots/browser/controlpanel.py
collective/z3cform/norobots/browser/interfaces.py
collective/z3cform/norobots/browser/norobots.py
collective/z3cform/norobots/browser/norobots_macro.pt
collective/z3cform/norobots/locales/collective.z3cform.norobots.pot
collective/z3cform/norobots/locales/manual.pot
collective/z3cform/norobots/locales/cs/LC_MESSAGES/collective.z3cform.norobots.po
collective/z3cform/norobots/locales/da/LC_MESSAGES/collective.z3cform.norobots.po
collective/z3cform/norobots/locales/de/LC_MESSAGES/collective.z3cform.norobots.po
collective/z3cform/norobots/locales/en/LC_MESSAGES/collective.z3cform.norobots.po
collective/z3cform/norobots/locales/es/LC_MESSAGES/collective.z3cform.norobots.po
collective/z3cform/norobots/locales/eu/LC_MESSAGES/collective.z3cform.norobots.po
collective/z3cform/norobots/locales/fi/LC_MESSAGES/collective.z3cform.norobots.po
collective/z3cform/norobots/locales/fr/LC_MESSAGES/collective.z3cform.norobots.po
collective/z3cform/norobots/locales/it/LC_MESSAGES/collective.z3cform.norobots.po
collective/z3cform/norobots/locales/nl/LC_MESSAGES/collective.z3cform.norobots.po
collective/z3cform/norobots/locales/ru/LC_MESSAGES/collective.z3cform.norobots.po
collective/z3cform/norobots/locales/zh_CN/LC_MESSAGES/collective.z3cform.norobots.po
collective.z3cform.norobots-3.0.dist-info/LICENSE.txt
collective.z3cform.norobots-3.0.dist-info/METADATA
collective.z3cform.norobots-3.0.dist-info/WHEEL
collective.z3cform.norobots-3.0.dist-info/entry_points.txt
collective.z3cform.norobots-3.0.dist-info/namespace_packages.txt
collective.z3cform.norobots-3.0.dist-info/top_level.txt
collective.z3cform.norobots-3.0.dist-info/RECORD
