Metadata-Version: 2.1
Name: collective.z3cform.norobots
Version: 3.0
Summary: Human readable captcha for z3cform
Home-page: http://www.makina-corpus.com
Author: Sylvain Boureliou
Author-email: sylvain.boureliou@makina-corpus.com
License: GPL
Keywords: plone z3cform captcha
Classifier: Development Status :: 5 - Production/Stable
Classifier: Framework :: Plone
Classifier: Framework :: Plone :: Addon
Classifier: Framework :: Plone :: 6.0
Classifier: Framework :: Plone :: 6.1
Classifier: Programming Language :: Python
Classifier: Programming Language :: Python :: 3.8
Classifier: Programming Language :: Python :: 3.9
Classifier: Programming Language :: Python :: 3.10
Classifier: Programming Language :: Python :: 3.11
Classifier: Programming Language :: Python :: 3.12
Classifier: Topic :: Software Development :: Libraries :: Python Modules
Classifier: License :: OSI Approved :: GNU General Public License (GPL)
Requires-Python: >=3.8
License-File: LICENSE.txt
Requires-Dist: setuptools
Requires-Dist: plone.app.registry
Requires-Dist: plone.registry
Requires-Dist: plone.restapi
Requires-Dist: Zope
Requires-Dist: Products.CMFPlone
Requires-Dist: Products.GenericSetup
Requires-Dist: z3c.form
Requires-Dist: plone.base
Provides-Extra: test
Requires-Dist: plone.app.testing ; extra == 'test'
Requires-Dist: plone.api ; extra == 'test'
Requires-Dist: plone.browserlayer ; extra == 'test'
Requires-Dist: plone.testing >=5.0.0 ; extra == 'test'
Requires-Dist: six ; extra == 'test'
Requires-Dist: lxml ; extra == 'test'
